valgrind_codequality/__init__.py
valgrind_codequality/__main__.py
valgrind_codequality-1.3.1.dist-info/LICENSE
valgrind_codequality-1.3.1.dist-info/METADATA
valgrind_codequality-1.3.1.dist-info/WHEEL
valgrind_codequality-1.3.1.dist-info/entry_points.txt
valgrind_codequality-1.3.1.dist-info/RECORD
