Metadata-Version: 2.3
Name: valgrind-codequality
Version: 1.3.1
Summary: Convert Valgrind XML to GitLab Code Quality JSON file.
License: MIT
Author: Arnaud Moura
Author-email: arnaudmoura@gmail.com
Requires-Python: >=3.10,<3.14
Classifier: License :: OSI Approved :: MIT License
Classifier: Programming Language :: Python :: 3
Classifier: Programming Language :: Python :: 3.10
Classifier: Programming Language :: Python :: 3.11
Classifier: Programming Language :: Python :: 3.12
Classifier: Programming Language :: Python :: 3.13
Requires-Dist: xmltodict (>=0.13.0,<0.14.0)
Project-URL: Bug Tracker, https://gitlab.com/EchoPouet/valgrind-codequality/-/issues
Project-URL: Changelog, https://gitlab.com/EchoPouet/valgrind-codequality/-/blob/main/CHANGELOG.md
